ETAES/ETAES_startapp.py
ETAES/__init__.py
ETAES/components.py
ETAES/operations.py
ETAES/pipeline.py
ETAES/globals/__init__.py
ETAES/globals/mapItem.py
ETAES/prototype/README.md.py
ETAES/prototype/README_CN.md.py
ETAES/prototype/__init__.py
ETAES/prototype/install.sh.py
ETAES/prototype/requirements.txt.py
ETAES/prototype/setup.py
ETAES/prototype/prototype/__init__.py
ETAES/prototype/prototype/main.py
ETAES/prototype/prototype/cfgs/__init__.py
ETAES/prototype/prototype/cfgs/config.yaml.py
ETAES/prototype/prototype/data/__init__.py
ETAES/prototype/prototype/externals/__init__.py
ETAES/prototype/prototype/externals/my.py
ETAES/utils/__init__.py
ETAES/utils/builder.py
ETAES/utils/globals.py
ETAES/utils/logging.py
ETAES/utils/mapping.py
externals/__init__.py
externals/my.py
prototype/README.md.py
prototype/README_CN.md.py
prototype/__init__.py
prototype/install.sh.py
prototype/requirements.txt.py
prototype/prototype/__init__.py
prototype/prototype/externals/__init__.py
prototype/prototype/externals/my.py
ttt/__init__.py
ttt/ttt/__init__.py
ttt/ttt/externals/__init__.py
ttt/ttt/externals/my.py
ETAES-0.0.49.dist-info/METADATA
ETAES-0.0.49.dist-info/WHEEL
ETAES-0.0.49.dist-info/top_level.txt
ETAES-0.0.49.dist-info/RECORD
